proSVD.py
pro_utils.py
proSVD-0.0.1.dist-info/LICENSE
proSVD-0.0.1.dist-info/METADATA
proSVD-0.0.1.dist-info/WHEEL
proSVD-0.0.1.dist-info/top_level.txt
proSVD-0.0.1.dist-info/RECORD
